etherscanwrapper/__init__.py
etherscanwrapper/etherscanwrapper.py
etherscanwrapper-0.1.0.dist-info/METADATA
etherscanwrapper-0.1.0.dist-info/WHEEL
etherscanwrapper-0.1.0.dist-info/top_level.txt
etherscanwrapper-0.1.0.dist-info/RECORD
