Metadata-Version: 2.1
Name: etherscanwrapper
Version: 0.1.0
Summary: Blah.
Home-page: https://github.com/walkentalk/etherscanwrapper
Author: Walken Talk
Author-email: walkentalk@pm.me
License: MIT license
Keywords: etherscanwrapper
Platform: UNKNOWN
Requires-Python: >=3.6
